mecab2pandas/__init__.py
mecab2pandas/__version__.py
mecab2pandas/exception/__init__.py
mecab2pandas/exception/exceptions.py
mecab2pandas/mecab_parser.py
mecab2pandas-0.2.3.dist-info/LICENSE
mecab2pandas-0.2.3.dist-info/WHEEL
mecab2pandas-0.2.3.dist-info/METADATA
mecab2pandas-0.2.3.dist-info/RECORD
