Metadata-Version: 2.1
Name: mecab2pandas
Version: 0.2.3
Summary: MeCab to pandas
Home-page: https://github.com/Lucky-Mano/mecab2pandas
License: MIT
Author: Lucky
Author-email: phatbowie@gmail.com
Requires-Python: >=3.7,<4.0
Classifier: License :: OSI Approved :: MIT License
Classifier: Programming Language :: Python :: 3
Classifier: Programming Language :: Python :: 3.10
Classifier: Programming Language :: Python :: 3.7
Classifier: Programming Language :: Python :: 3.8
Classifier: Programming Language :: Python :: 3.9
Requires-Dist: mecab-python3
Requires-Dist: pandas
Requires-Dist: unidic-lite
